gql_ext/__init__.py
gql_ext/config.py
gql_ext/dataloaders.py
gql_ext/exceptions.py
gql_ext/main.py
gql_ext/utils.py
gql_ext/view.py
gql_ext/clients/__init__.py
gql_ext/clients/base.py
gql_ext/clients/http/__init__.py
gql_ext/clients/http/base.py
gql_ext/clients/http/http_api.py
gql_ext/clients/http/requests.py
gql_ext/graphiql/__init__.py
gql_ext/graphiql/graphiql.html
gql_ext/graphiql/graphiql.py
gql_ext/resolvers/__init__.py
gql_ext/resolvers/resolver_cls_creator.py
gql_ext/resolvers/set_resolver.py
gql_ext/resolvers/base_resolvers/__init__.py
gql_ext/resolvers/base_resolvers/base.py
gql_ext/resolvers/base_resolvers/mutation.py
gql_ext/resolvers/base_resolvers/query.py
gql_ext/resolvers/base_resolvers/subscription.py
gql_ext/websocket/__init__.py
gql_ext/websocket/constants.py
gql_ext/websocket/context_factory.py
gql_ext/websocket/main.py
gql_ext/websocket/subscription_ws_handler.py
gql_ext-1.0.2.data/data/LICENSE
gql_ext-1.0.2.dist-info/LICENSE
gql_ext-1.0.2.dist-info/METADATA
gql_ext-1.0.2.dist-info/WHEEL
gql_ext-1.0.2.dist-info/top_level.txt
gql_ext-1.0.2.dist-info/RECORD
