Metadata-Version: 2.1
Name: gql-ext
Version: 1.0.2
Summary: The web framework
Home-page: https://github.com/PonomarevMaksim/bff-graphql
Author: Max Ponomarev
Author-email: ponomarev1802@mail.ru
License: BSD
Platform: UNKNOWN
Classifier: Development Status :: 3 - Alpha
Classifier: Environment :: Web Environment
Classifier: Intended Audience :: Developers
Classifier: License :: OSI Approved :: BSD License
Classifier: Operating System :: OS Independent
Classifier: Topic :: Internet :: WWW/HTTP
Classifier: Programming Language :: Python :: 3.7
Requires-Python: >=3.7
Requires-Dist: aiodataloader (==0.1.2)
Requires-Dist: aiohttp (==3.6.2)
Requires-Dist: pyyaml (==5.1.2)
Requires-Dist: tartiflette (==0.12.4)
